saw_client/__init__.py
saw_client/commands.py
saw_client/connection.py
saw_client/crucible.py
saw_client/dashboard.py
saw_client/exceptions.py
saw_client/jvm.py
saw_client/jvm_type.py
saw_client/llvm.py
saw_client/llvm_type.py
saw_client/mir.py
saw_client/mir_type.py
saw_client/option.py
saw_client/proofscript.py
saw_client/py.typed
saw_client/solver_cache.py
saw_client/utils.py
saw_client-1.4.dist-info/METADATA
saw_client-1.4.dist-info/WHEEL
saw_client-1.4.dist-info/RECORD
