Metadata-Version: 2.4
Name: saw-client
Version: 1.4
Summary: SAW client for the SAW RPC server
License: BSD License
Author: Galois, Inc.
Author-email: saw@galois.com
Requires-Python: >=3.9,<4.0
Classifier: License :: Other/Proprietary License
Classifier: Programming Language :: Python :: 3
Classifier: Programming Language :: Python :: 3.9
Classifier: Programming Language :: Python :: 3.10
Classifier: Programming Language :: Python :: 3.11
Classifier: Programming Language :: Python :: 3.12
Classifier: Programming Language :: Python :: 3.13
Classifier: Programming Language :: Python :: 3.14
Requires-Dist: BitVector (>=3.4.9,<4.0.0)
Requires-Dist: argo-client (>=0.0.13)
Requires-Dist: cbor2 (>=5.4.6,<6.0.0)
Requires-Dist: cryptol (==3.3)
Requires-Dist: lmdb (>=1.6.2,<2.0.0)
Requires-Dist: python-dateutil (>=2.8.2,<3.0.0)
Requires-Dist: requests (>=2.25.1,<3.0.0)
Requires-Dist: urllib3 (>=2.5.0)
